dbilib/__init__.py
dbilib/_dbi_base.py
dbilib/_dbi_mssql.py
dbilib/_dbi_mysql.py
dbilib/_dbi_oracle.py
dbilib/_dbi_sqlite.py
dbilib/_version.py
dbilib/changelog.py
dbilib/database.py
dbilib-0.5.1.dist-info/licenses/LICENSE
dbilib-0.5.1.dist-info/METADATA
dbilib-0.5.1.dist-info/WHEEL
dbilib-0.5.1.dist-info/top_level.txt
dbilib-0.5.1.dist-info/RECORD
