Metadata-Version: 2.4
Name: dbilib
Version: 0.5.1
Summary: A generalised and simple database interface library.
Author-email: The Developers <development@s3dev.uk>
License-Expression: MIT
Project-URL: Documentation, https://dbilib.readthedocs.io/en/latest/
Project-URL: Homepage, https://github.com/s3dev/dbilib
Project-URL: Repository, https://github.com/s3dev/dbilib
Keywords: database,interface,utilities
Classifier: Development Status :: 5 - Production/Stable
Classifier: Intended Audience :: Developers
Classifier: Operating System :: POSIX :: Linux
Classifier: Operating System :: Microsoft :: Windows
Classifier: Programming Language :: Python :: 3.10
Classifier: Programming Language :: Python :: 3.11
Classifier: Programming Language :: Python :: 3.12
Classifier: Programming Language :: Python :: 3.13
Classifier: Topic :: Software Development
Classifier: Topic :: Software Development :: Libraries
Classifier: Topic :: Utilities
Requires-Python: >=3.10
License-File: LICENSE
Requires-Dist: pandas>=2.0
Requires-Dist: sqlalchemy>=2.0
Requires-Dist: utils4>=1.0.0
Dynamic: license-file
